{"MRData":{"xmlns":"","series":"f1","url":"https://api.jolpi.ca/ergast/f1/1953/drivers/rathmann/results/","limit":"30","offset":"0","total":"2","RaceTable":{"season":"1953","driverId":"rathmann","Races":[{"season":"1953","round":"2","url":"https://en.wikipedia.org/wiki/1953_Indianapolis_500","raceName":"Indianapolis 500","Circuit":{"circuitId":"indianapolis","url":"https://en.wikipedia.org/wiki/Indianapolis_Motor_Speedway","circuitName":"Indianapolis Motor Speedway","Location":{"lat":"39.795","long":"-86.2347","locality":"Indianapolis","country":"USA"}},"date":"1953-05-30","Results":[{"number":"2","position":"7","positionText":"7","points":"0","Driver":{"driverId":"rathmann","url":"http://en.wikipedia.org/wiki/Jim_Rathmann","givenName":"Jim","familyName":"Rathmann","dateOfBirth":"1928-07-16","nationality":"American"},"Constructor":{"constructorId":"kurtis_kraft","url":"http://en.wikipedia.org/wiki/Kurtis_Kraft","name":"Kurtis Kraft","nationality":"American"},"grid":"25","laps":"200","status":"Finished","Time":{"millis":"14507710","time":"+8:46.020"}},{"number":"49","position":"15","positionText":"15","points":"0","Driver":{"driverId":"rathmann","url":"http://en.wikipedia.org/wiki/Jim_Rathmann","givenName":"Jim","familyName":"Rathmann","dateOfBirth":"1928-07-16","nationality":"American"},"Constructor":{"constructorId":"kurtis_kraft","url":"http://en.wikipedia.org/wiki/Kurtis_Kraft","name":"Kurtis Kraft","nationality":"American"},"grid":"28","laps":"177","status":"Magneto"}]}]}}}