{"MRData":{"xmlns":"","series":"f1","url":"https://api.jolpi.ca/ergast/f1/1979/drivers/rebaque/results/","limit":"30","offset":"0","total":"10","RaceTable":{"season":"1979","driverId":"rebaque","Races":[{"season":"1979","round":"1","url":"https://en.wikipedia.org/wiki/1979_Argentine_Grand_Prix","raceName":"Argentine Grand Prix","Circuit":{"circuitId":"galvez","url":"https://en.wikipedia.org/wiki/Aut칩dromo_Oscar_y_Juan_G치lvez","circuitName":"Aut칩dromo Juan y Oscar G치lvez","Location":{"lat":"-34.6943","long":"-58.4593","locality":"Buenos Aires","country":"Argentina"}},"date":"1979-01-21","Results":[{"number":"31","position":"13","positionText":"R","points":"0","Driver":{"driverId":"rebaque","url":"http://en.wikipedia.org/wiki/Hector_Rebaque","givenName":"Hector","familyName":"Rebaque","dateOfBirth":"1956-02-05","nationality":"Mexican"},"Constructor":{"constructorId":"team_lotus","url":"http://en.wikipedia.org/wiki/Team_Lotus","name":"Team Lotus","nationality":"British"},"grid":"19","laps":"46","status":"Suspension"}]},{"season":"1979","round":"3","url":"https://en.wikipedia.org/wiki/1979_South_African_Grand_Prix","raceName":"South African Grand Prix","Circuit":{"circuitId":"kyalami","url":"https://en.wikipedia.org/wiki/Kyalami","circuitName":"Kyalami","Location":{"lat":"-25.9894","long":"28.0767","locality":"Midrand","country":"South Africa"}},"date":"1979-03-03","Results":[{"number":"31","position":"14","positionText":"R","points":"0","Driver":{"driverId":"rebaque","url":"http://en.wikipedia.org/wiki/Hector_Rebaque","givenName":"Hector","familyName":"Rebaque","dateOfBirth":"1956-02-05","nationality":"Mexican"},"Constructor":{"constructorId":"team_lotus","url":"http://en.wikipedia.org/wiki/Team_Lotus","name":"Team Lotus","nationality":"British"},"grid":"23","laps":"71","status":"Engine"}]},{"season":"1979","round":"4","url":"https://en.wikipedia.org/wiki/1979_United_States_Grand_Prix_West","raceName":"United States Grand Prix West","Circuit":{"circuitId":"long_beach","url":"https://en.wikipedia.org/wiki/Long_Beach,_California","circuitName":"Long Beach","Location":{"lat":"33.7651","long":"-118.189","locality":"California","country":"USA"}},"date":"1979-04-08","Results":[{"number":"31","position":"11","positionText":"R","points":"0","Driver":{"driverId":"rebaque","url":"http://en.wikipedia.org/wiki/Hector_Rebaque","givenName":"Hector","familyName":"Rebaque","dateOfBirth":"1956-02-05","nationality":"Mexican"},"Constructor":{"constructorId":"team_lotus","url":"http://en.wikipedia.org/wiki/Team_Lotus","name":"Team Lotus","nationality":"British"},"grid":"23","laps":"71","status":"Accident"}]},{"season":"1979","round":"5","url":"https://en.wikipedia.org/wiki/1979_Spanish_Grand_Prix","raceName":"Spanish Grand Prix","Circuit":{"circuitId":"jarama","url":"https://en.wikipedia.org/wiki/Circuito_del_Jarama","circuitName":"Jarama","Location":{"lat":"40.6171","long":"-3.58558","locality":"Madrid","country":"Spain"}},"date":"1979-04-29","Results":[{"number":"31","position":"16","positionText":"R","points":"0","Driver":{"driverId":"rebaque","url":"http://en.wikipedia.org/wiki/Hector_Rebaque","givenName":"Hector","familyName":"Rebaque","dateOfBirth":"1956-02-05","nationality":"Mexican"},"Constructor":{"constructorId":"team_lotus","url":"http://en.wikipedia.org/wiki/Team_Lotus","name":"Team Lotus","nationality":"British"},"grid":"23","laps":"58","status":"Engine"}]},{"season":"1979","round":"6","url":"https://en.wikipedia.org/wiki/1979_Belgian_Grand_Prix","raceName":"Belgian Grand Prix","Circuit":{"circuitId":"zolder","url":"https://en.wikipedia.org/wiki/Circuit_Zolder","circuitName":"Zolder","Location":{"lat":"50.9894","long":"5.25694","locality":"Heusden-Zolder","country":"Belgium"}},"date":"1979-05-13","Results":[{"number":"31","position":"22","positionText":"R","points":"0","Driver":{"driverId":"rebaque","url":"http://en.wikipedia.org/wiki/Hector_Rebaque","givenName":"Hector","familyName":"Rebaque","dateOfBirth":"1956-02-05","nationality":"Mexican"},"Constructor":{"constructorId":"team_lotus","url":"http://en.wikipedia.org/wiki/Team_Lotus","name":"Team Lotus","nationality":"British"},"grid":"15","laps":"13","status":"Transmission"}]},{"season":"1979","round":"8","url":"https://en.wikipedia.org/wiki/1979_French_Grand_Prix","raceName":"French Grand Prix","Circuit":{"circuitId":"dijon","url":"https://en.wikipedia.org/wiki/Dijon-Prenois","circuitName":"Dijon-Prenois","Location":{"lat":"47.3625","long":"4.89913","locality":"Dijon","country":"France"}},"date":"1979-07-01","Results":[{"number":"31","position":"12","positionText":"12","points":"0","Driver":{"driverId":"rebaque","url":"http://en.wikipedia.org/wiki/Hector_Rebaque","givenName":"Hector","familyName":"Rebaque","dateOfBirth":"1956-02-05","nationality":"Mexican"},"Constructor":{"constructorId":"team_lotus","url":"http://en.wikipedia.org/wiki/Team_Lotus","name":"Team Lotus","nationality":"British"},"grid":"23","laps":"78","status":"+2 Laps"}]},{"season":"1979","round":"9","url":"https://en.wikipedia.org/wiki/1979_British_Grand_Prix","raceName":"British Grand Prix","Circuit":{"circuitId":"silverstone","url":"https://en.wikipedia.org/wiki/Silverstone_Circuit","circuitName":"Silverstone Circuit","Location":{"lat":"52.0786","long":"-1.01694","locality":"Silverstone","country":"UK"}},"date":"1979-07-14","Results":[{"number":"31","position":"9","positionText":"9","points":"0","Driver":{"driverId":"rebaque","url":"http://en.wikipedia.org/wiki/Hector_Rebaque","givenName":"Hector","familyName":"Rebaque","dateOfBirth":"1956-02-05","nationality":"Mexican"},"Constructor":{"constructorId":"team_lotus","url":"http://en.wikipedia.org/wiki/Team_Lotus","name":"Team Lotus","nationality":"British"},"grid":"26","laps":"66","status":"+2 Laps"}]},{"season":"1979","round":"10","url":"https://en.wikipedia.org/wiki/1979_German_Grand_Prix","raceName":"German Grand Prix","Circuit":{"circuitId":"hockenheimring","url":"https://en.wikipedia.org/wiki/Hockenheimring","circuitName":"Hockenheimring","Location":{"lat":"49.3278","long":"8.56583","locality":"Hockenheim","country":"Germany"}},"date":"1979-07-29","Results":[{"number":"31","position":"18","positionText":"R","points":"0","Driver":{"driverId":"rebaque","url":"http://en.wikipedia.org/wiki/Hector_Rebaque","givenName":"Hector","familyName":"Rebaque","dateOfBirth":"1956-02-05","nationality":"Mexican"},"Constructor":{"constructorId":"team_lotus","url":"http://en.wikipedia.org/wiki/Team_Lotus","name":"Team Lotus","nationality":"British"},"grid":"24","laps":"22","status":"Handling"}]},{"season":"1979","round":"12","url":"https://en.wikipedia.org/wiki/1979_Dutch_Grand_Prix","raceName":"Dutch Grand Prix","Circuit":{"circuitId":"zandvoort","url":"https://en.wikipedia.org/wiki/Circuit_Zandvoort","circuitName":"Circuit Park Zandvoort","Location":{"lat":"52.3888","long":"4.54092","locality":"Zandvoort","country":"Netherlands"}},"date":"1979-08-26","Results":[{"number":"31","position":"7","positionText":"7","points":"0","Driver":{"driverId":"rebaque","url":"http://en.wikipedia.org/wiki/Hector_Rebaque","givenName":"Hector","familyName":"Rebaque","dateOfBirth":"1956-02-05","nationality":"Mexican"},"Constructor":{"constructorId":"team_lotus","url":"http://en.wikipedia.org/wiki/Team_Lotus","name":"Team Lotus","nationality":"British"},"grid":"24","laps":"73","status":"+2 Laps"}]},{"season":"1979","round":"14","url":"https://en.wikipedia.org/wiki/1979_Canadian_Grand_Prix","raceName":"Canadian Grand Prix","Circuit":{"circuitId":"villeneuve","url":"https://en.wikipedia.org/wiki/Circuit_Gilles_Villeneuve","circuitName":"Circuit Gilles Villeneuve","Location":{"lat":"45.5","long":"-73.5228","locality":"Montreal","country":"Canada"}},"date":"1979-09-30","Results":[{"number":"31","position":"16","positionText":"R","points":"0","Driver":{"driverId":"rebaque","url":"http://en.wikipedia.org/wiki/Hector_Rebaque","givenName":"Hector","familyName":"Rebaque","dateOfBirth":"1956-02-05","nationality":"Mexican"},"Constructor":{"constructorId":"rebaque","url":"http://en.wikipedia.org/wiki/Rebaque","name":"Rebaque","nationality":"Mexican"},"grid":"22","laps":"26","status":"Chassis"}]}]}}}