{"MRData":{"xmlns":"","series":"f1","url":"https://api.jolpi.ca/ergast/f1/1971/drivers/hailwood/results/","limit":"30","offset":"0","total":"2","RaceTable":{"season":"1971","driverId":"hailwood","Races":[{"season":"1971","round":"9","url":"https://en.wikipedia.org/wiki/1971_Italian_Grand_Prix","raceName":"Italian Grand Prix","Circuit":{"circuitId":"monza","url":"https://en.wikipedia.org/wiki/Monza_Circuit","circuitName":"Autodromo Nazionale di Monza","Location":{"lat":"45.6156","long":"9.28111","locality":"Monza","country":"Italy"}},"date":"1971-09-05","Results":[{"number":"9","position":"4","positionText":"4","points":"3","Driver":{"driverId":"hailwood","url":"http://en.wikipedia.org/wiki/Mike_Hailwood","givenName":"Mike","familyName":"Hailwood","dateOfBirth":"1940-04-02","nationality":"British"},"Constructor":{"constructorId":"surtees","url":"http://en.wikipedia.org/wiki/Surtees","name":"Surtees","nationality":"British"},"grid":"17","laps":"55","status":"Finished","Time":{"millis":"4692780","time":"+0.180"}}]},{"season":"1971","round":"11","url":"https://en.wikipedia.org/wiki/1971_United_States_Grand_Prix","raceName":"United States Grand Prix","Circuit":{"circuitId":"watkins_glen","url":"https://en.wikipedia.org/wiki/Watkins_Glen_International","circuitName":"Watkins Glen","Location":{"lat":"42.3369","long":"-76.9272","locality":"New York State","country":"USA"}},"date":"1971-10-03","Results":[{"number":"20","position":"15","positionText":"15","points":"0","Driver":{"driverId":"hailwood","url":"http://en.wikipedia.org/wiki/Mike_Hailwood","givenName":"Mike","familyName":"Hailwood","dateOfBirth":"1940-04-02","nationality":"British"},"Constructor":{"constructorId":"surtees","url":"http://en.wikipedia.org/wiki/Surtees","name":"Surtees","nationality":"British"},"grid":"14","laps":"54","status":"Accident"}]}]}}}