{"MRData":{"xmlns":"","series":"f1","url":"https://api.jolpi.ca/ergast/f1/1959/5/results/","limit":"30","offset":"0","total":"24","RaceTable":{"season":"1959","round":"5","Races":[{"season":"1959","round":"5","url":"https://en.wikipedia.org/wiki/1959_British_Grand_Prix","raceName":"British Grand Prix","Circuit":{"circuitId":"aintree","url":"https://en.wikipedia.org/wiki/Aintree_Motor_Racing_Circuit","circuitName":"Aintree","Location":{"lat":"53.4769","long":"-2.94056","locality":"Liverpool","country":"UK"}},"date":"1959-07-18","Results":[{"number":"12","position":"1","positionText":"1","points":"8","Driver":{"driverId":"jack_brabham","url":"http://en.wikipedia.org/wiki/Jack_Brabham","givenName":"Jack","familyName":"Brabham","dateOfBirth":"1926-04-02","nationality":"Australian"},"Constructor":{"constructorId":"cooper-climax","url":"http://en.wikipedia.org/wiki/Cooper_Car_Company","name":"Cooper-Climax","nationality":"British"},"grid":"1","laps":"75","status":"Finished","Time":{"millis":"9011600","time":"2:30:11.600"}},{"number":"6","position":"2","positionText":"2","points":"6.5","Driver":{"driverId":"moss","url":"http://en.wikipedia.org/wiki/Stirling_Moss","givenName":"Stirling","familyName":"Moss","dateOfBirth":"1929-09-17","nationality":"British"},"Constructor":{"constructorId":"brm","url":"http://en.wikipedia.org/wiki/BRM","name":"BRM","nationality":"British"},"grid":"7","laps":"75","status":"Finished","Time":{"millis":"9033800","time":"+22.200"}},{"number":"16","position":"3","positionText":"3","points":"4.5","Driver":{"driverId":"mclaren","url":"http://en.wikipedia.org/wiki/Bruce_McLaren","givenName":"Bruce","familyName":"McLaren","dateOfBirth":"1937-08-30","nationality":"New Zealander"},"Constructor":{"constructorId":"cooper-climax","url":"http://en.wikipedia.org/wiki/Cooper_Car_Company","name":"Cooper-Climax","nationality":"British"},"grid":"8","laps":"75","status":"Finished","Time":{"millis":"9034000","time":"+22.400"}},{"number":"8","position":"4","positionText":"4","points":"3","Driver":{"driverId":"schell","url":"http://en.wikipedia.org/wiki/Harry_Schell","givenName":"Harry","familyName":"Schell","dateOfBirth":"1921-06-29","nationality":"American"},"Constructor":{"constructorId":"brm","url":"http://en.wikipedia.org/wiki/BRM","name":"BRM","nationality":"British"},"grid":"3","laps":"74","status":"+1 Lap"},{"number":"18","position":"5","positionText":"5","points":"2","Driver":{"driverId":"trintignant","url":"http://en.wikipedia.org/wiki/Maurice_Trintignant","givenName":"Maurice","familyName":"Trintignant","dateOfBirth":"1917-10-30","nationality":"French"},"Constructor":{"constructorId":"cooper-climax","url":"http://en.wikipedia.org/wiki/Cooper_Car_Company","name":"Cooper-Climax","nationality":"British"},"grid":"4","laps":"74","status":"+1 Lap"},{"number":"2","position":"6","positionText":"6","points":"0","Driver":{"driverId":"salvadori","url":"http://en.wikipedia.org/wiki/Roy_Salvadori","givenName":"Roy","familyName":"Salvadori","dateOfBirth":"1922-05-12","nationality":"British"},"Constructor":{"constructorId":"aston_martin","url":"http://en.wikipedia.org/wiki/Aston_Martin_in_Formula_One","name":"Aston Martin","nationality":"British"},"grid":"2","laps":"74","status":"+1 Lap"},{"number":"14","position":"7","positionText":"7","points":"0","Driver":{"driverId":"gregory","url":"http://en.wikipedia.org/wiki/Masten_Gregory","givenName":"Masten","familyName":"Gregory","dateOfBirth":"1932-02-29","nationality":"American"},"Constructor":{"constructorId":"cooper-climax","url":"http://en.wikipedia.org/wiki/Cooper_Car_Company","name":"Cooper-Climax","nationality":"British"},"grid":"5","laps":"73","status":"+2 Laps"},{"number":"30","position":"8","positionText":"8","points":"0","Driver":{"driverId":"stacey","url":"http://en.wikipedia.org/wiki/Alan_Stacey","givenName":"Alan","familyName":"Stacey","dateOfBirth":"1933-08-29","nationality":"British"},"Constructor":{"constructorId":"team_lotus","url":"http://en.wikipedia.org/wiki/Team_Lotus","name":"Team Lotus","nationality":"British"},"grid":"12","laps":"71","status":"+4 Laps"},{"number":"28","position":"9","positionText":"9","points":"0","Driver":{"driverId":"hill","url":"http://en.wikipedia.org/wiki/Graham_Hill","givenName":"Graham","familyName":"Hill","dateOfBirth":"1929-02-15","nationality":"British"},"Constructor":{"constructorId":"team_lotus","url":"http://en.wikipedia.org/wiki/Team_Lotus","name":"Team Lotus","nationality":"British"},"grid":"9","laps":"70","status":"+5 Laps"},{"number":"48","position":"10","positionText":"10","points":"0","Driver":{"driverId":"bristow","url":"http://en.wikipedia.org/wiki/Chris_Bristow","givenName":"Chris","familyName":"Bristow","dateOfBirth":"1937-12-02","nationality":"British"},"Constructor":{"constructorId":"cooper-borgward","url":"http://en.wikipedia.org/wiki/Cooper_Car_Company","name":"Cooper-Borgward","nationality":"British"},"grid":"16","laps":"70","status":"+5 Laps"},{"number":"58","position":"11","positionText":"11","points":"0","Driver":{"driverId":"henry_taylor","url":"http://en.wikipedia.org/wiki/Henry_Taylor_(racing_driver)","givenName":"Henry","familyName":"Taylor","dateOfBirth":"1932-12-16","nationality":"British"},"Constructor":{"constructorId":"cooper-climax","url":"http://en.wikipedia.org/wiki/Cooper_Car_Company","name":"Cooper-Climax","nationality":"British"},"grid":"21","laps":"69","status":"+6 Laps"},{"number":"52","position":"12","positionText":"12","points":"0","Driver":{"driverId":"ashdown","url":"http://en.wikipedia.org/wiki/Peter_Ashdown","givenName":"Peter","familyName":"Ashdown","dateOfBirth":"1934-10-16","nationality":"British"},"Constructor":{"constructorId":"cooper-climax","url":"http://en.wikipedia.org/wiki/Cooper_Car_Company","name":"Cooper-Climax","nationality":"British"},"grid":"23","laps":"69","status":"+6 Laps"},{"number":"46","position":"13","positionText":"13","points":"0","Driver":{"driverId":"bueb","url":"http://en.wikipedia.org/wiki/Ivor_Bueb","givenName":"Ivor","familyName":"Bueb","dateOfBirth":"1923-06-06","nationality":"British"},"Constructor":{"constructorId":"cooper-borgward","url":"http://en.wikipedia.org/wiki/Cooper_Car_Company","name":"Cooper-Borgward","nationality":"British"},"grid":"18","laps":"69","status":"+6 Laps"},{"number":"4","position":"14","positionText":"R","points":"0","Driver":{"driverId":"shelby","url":"http://en.wikipedia.org/wiki/Carroll_Shelby","givenName":"Carroll","familyName":"Shelby","dateOfBirth":"1923-01-11","nationality":"American"},"Constructor":{"constructorId":"aston_martin","url":"http://en.wikipedia.org/wiki/Aston_Martin_in_Formula_One","name":"Aston Martin","nationality":"British"},"grid":"6","laps":"69","status":"Ignition"},{"number":"40","position":"15","positionText":"R","points":"0","Driver":{"driverId":"orey","url":"http://en.wikipedia.org/wiki/Fritz_d%27Orey","givenName":"Fritz","familyName":"d'Orey","dateOfBirth":"1938-03-25","nationality":"Brazilian"},"Constructor":{"constructorId":"maserati","url":"http://en.wikipedia.org/wiki/Maserati","name":"Maserati","nationality":"Italian"},"grid":"20","laps":"57","status":"Accident"},{"number":"42","position":"16","positionText":"R","points":"0","Driver":{"driverId":"flockhart","url":"http://en.wikipedia.org/wiki/Ron_Flockhart_(auto_racing)","givenName":"Ron","familyName":"Flockhart","dateOfBirth":"1923-06-16","nationality":"British"},"Constructor":{"constructorId":"brm","url":"http://en.wikipedia.org/wiki/BRM","name":"BRM","nationality":"British"},"grid":"11","laps":"53","status":"Spun off"},{"number":"38","position":"17","positionText":"R","points":"0","Driver":{"driverId":"fairman","url":"http://en.wikipedia.org/wiki/Jack_Fairman","givenName":"Jack","familyName":"Fairman","dateOfBirth":"1913-03-15","nationality":"British"},"Constructor":{"constructorId":"cooper-climax","url":"http://en.wikipedia.org/wiki/Cooper_Car_Company","name":"Cooper-Climax","nationality":"British"},"grid":"15","laps":"39","status":"Gearbox"},{"number":"10","position":"18","positionText":"R","points":"0","Driver":{"driverId":"bonnier","url":"http://en.wikipedia.org/wiki/Joakim_Bonnier","givenName":"Jo","familyName":"Bonnier","dateOfBirth":"1930-01-31","nationality":"Swedish"},"Constructor":{"constructorId":"brm","url":"http://en.wikipedia.org/wiki/BRM","name":"BRM","nationality":"British"},"grid":"10","laps":"37","status":"Brakes"},{"number":"22","position":"19","positionText":"R","points":"0","Driver":{"driverId":"burgess","url":"http://en.wikipedia.org/wiki/Ian_Burgess","givenName":"Ian","familyName":"Burgess","dateOfBirth":"1930-07-06","nationality":"British"},"Constructor":{"constructorId":"cooper-maserati","url":"http://en.wikipedia.org/wiki/Cooper_Car_Company","name":"Cooper-Maserati","nationality":"British"},"grid":"13","laps":"31","status":"Transmission"},{"number":"24","position":"20","positionText":"R","points":"0","Driver":{"driverId":"herrmann","url":"http://en.wikipedia.org/wiki/Hans_Herrmann","givenName":"Hans","familyName":"Herrmann","dateOfBirth":"1928-02-23","nationality":"German"},"Constructor":{"constructorId":"cooper-maserati","url":"http://en.wikipedia.org/wiki/Cooper_Car_Company","name":"Cooper-Maserati","nationality":"British"},"grid":"19","laps":"21","status":"Gearbox"},{"number":"64","position":"21","positionText":"R","points":"0","Driver":{"driverId":"piper","url":"http://en.wikipedia.org/wiki/David_Piper","givenName":"David","familyName":"Piper","dateOfBirth":"1930-12-02","nationality":"British"},"Constructor":{"constructorId":"team_lotus","url":"http://en.wikipedia.org/wiki/Team_Lotus","name":"Team Lotus","nationality":"British"},"grid":"22","laps":"19","status":"Overheating"},{"number":"36","position":"22","positionText":"R","points":"0","Driver":{"driverId":"naylor","url":"http://en.wikipedia.org/wiki/Brian_Naylor","givenName":"Brian","familyName":"Naylor","dateOfBirth":"1923-03-24","nationality":"British"},"Constructor":{"constructorId":"jbw","url":"http://en.wikipedia.org/wiki/JBW","name":"JBW","nationality":"British"},"grid":"14","laps":"18","status":"Transmission"},{"number":"50","position":"23","positionText":"R","points":"0","Driver":{"driverId":"mike_taylor","url":"http://en.wikipedia.org/wiki/Mike_Taylor_(driver)","givenName":"Mike","familyName":"Taylor","dateOfBirth":"1934-04-24","nationality":"British"},"Constructor":{"constructorId":"cooper-climax","url":"http://en.wikipedia.org/wiki/Cooper_Car_Company","name":"Cooper-Climax","nationality":"British"},"grid":"24","laps":"17","status":"Transmission"},{"number":"20","position":"24","positionText":"R","points":"0","Driver":{"driverId":"brooks","url":"http://en.wikipedia.org/wiki/Tony_Brooks","givenName":"Tony","familyName":"Brooks","dateOfBirth":"1932-02-25","nationality":"British"},"Constructor":{"constructorId":"vanwall","url":"http://en.wikipedia.org/wiki/Vanwall","name":"Vanwall","nationality":"British"},"grid":"17","laps":"13","status":"Ignition"}]}]}}}