{"MRData":{"xmlns":"","series":"f1","url":"https://api.jolpi.ca/ergast/f1/1954/constructors/hwm/results/","limit":"30","offset":"0","total":"1","RaceTable":{"season":"1954","constructorId":"hwm","Races":[{"season":"1954","round":"4","url":"https://en.wikipedia.org/wiki/1954_French_Grand_Prix","raceName":"French Grand Prix","Circuit":{"circuitId":"reims","url":"https://en.wikipedia.org/wiki/Reims-Gueux","circuitName":"Reims-Gueux","Location":{"lat":"49.2542","long":"3.93083","locality":"Reims","country":"France"}},"date":"1954-07-04","Results":[{"number":"32","position":"17","positionText":"R","points":"0","Driver":{"driverId":"macklin","url":"http://en.wikipedia.org/wiki/Lance_Macklin","givenName":"Lance","familyName":"Macklin","dateOfBirth":"1919-09-02","nationality":"British"},"Constructor":{"constructorId":"hwm","url":"http://en.wikipedia.org/wiki/Hersham_and_Walton_Motors","name":"HWM","nationality":"British"},"grid":"15","laps":"10","status":"Engine"}]}]}}}