{"MRData":{"xmlns":"","series":"f1","url":"https://api.jolpi.ca/ergast/f1/1963/drivers/seiffert/results/","limit":"30","offset":"0","total":"1","RaceTable":{"season":"1963","driverId":"seiffert","Races":[{"season":"1963","round":"7","url":"https://en.wikipedia.org/wiki/1963_Italian_Grand_Prix","raceName":"Italian Grand Prix","Circuit":{"circuitId":"monza","url":"https://en.wikipedia.org/wiki/Monza_Circuit","circuitName":"Autodromo Nazionale di Monza","Location":{"lat":"45.6156","long":"9.28111","locality":"Monza","country":"Italy"}},"date":"1963-09-08","Results":[{"number":"52","position":"31","positionText":"W","points":"0","Driver":{"driverId":"seiffert","url":"http://en.wikipedia.org/wiki/G%C3%BCnther_Seiffert","givenName":"Günther","familyName":"Seiffert","dateOfBirth":"1937-10-18","nationality":"German"},"Constructor":{"constructorId":"lotus-brm","url":"http://en.wikipedia.org/wiki/Team_Lotus","name":"Lotus-BRM","nationality":"British"},"grid":"0","laps":"0","status":"Withdrew"}]}]}}}