{"MRData":{"xmlns":"","series":"f1","url":"https://api.jolpi.ca/ergast/f1/1964/7/results/","limit":"30","offset":"0","total":"20","RaceTable":{"season":"1964","round":"7","Races":[{"season":"1964","round":"7","url":"https://en.wikipedia.org/wiki/1964_Austrian_Grand_Prix","raceName":"Austrian Grand Prix","Circuit":{"circuitId":"zeltweg","url":"https://en.wikipedia.org/wiki/Zeltweg_Air_Base","circuitName":"Zeltweg","Location":{"lat":"47.2039","long":"14.7478","locality":"Styria","country":"Austria"}},"date":"1964-08-23","Results":[{"number":"8","position":"1","positionText":"1","points":"9","Driver":{"driverId":"bandini","url":"http://en.wikipedia.org/wiki/Lorenzo_Bandini","givenName":"Lorenzo","familyName":"Bandini","dateOfBirth":"1935-12-21","nationality":"Italian"},"Constructor":{"constructorId":"ferrari","url":"http://en.wikipedia.org/wiki/Scuderia_Ferrari","name":"Ferrari","nationality":"Italian"},"grid":"7","laps":"105","status":"Finished","Time":{"millis":"7578230","time":"2:06:18.230"}},{"number":"4","position":"2","positionText":"2","points":"6","Driver":{"driverId":"ginther","url":"http://en.wikipedia.org/wiki/Richie_Ginther","givenName":"Richie","familyName":"Ginther","dateOfBirth":"1930-08-05","nationality":"American"},"Constructor":{"constructorId":"brm","url":"http://en.wikipedia.org/wiki/BRM","name":"BRM","nationality":"British"},"grid":"5","laps":"105","status":"Finished","Time":{"millis":"7584410","time":"+6.180"}},{"number":"22","position":"3","positionText":"3","points":"4","Driver":{"driverId":"anderson","url":"http://en.wikipedia.org/wiki/Bob_Anderson_(racing_driver)","givenName":"Bob","familyName":"Anderson","dateOfBirth":"1931-05-19","nationality":"British"},"Constructor":{"constructorId":"brabham-climax","url":"http://en.wikipedia.org/wiki/Brabham","name":"Brabham-Climax","nationality":"British"},"grid":"14","laps":"102","status":"+3 Laps"},{"number":"19","position":"4","positionText":"4","points":"3","Driver":{"driverId":"maggs","url":"http://en.wikipedia.org/wiki/Tony_Maggs","givenName":"Tony","familyName":"Maggs","dateOfBirth":"1937-02-09","nationality":"South African"},"Constructor":{"constructorId":"brm","url":"http://en.wikipedia.org/wiki/BRM","name":"BRM","nationality":"British"},"grid":"19","laps":"102","status":"+3 Laps"},{"number":"14","position":"5","positionText":"5","points":"2","Driver":{"driverId":"ireland","url":"http://en.wikipedia.org/wiki/Innes_Ireland","givenName":"Innes","familyName":"Ireland","dateOfBirth":"1930-06-12","nationality":"British"},"Constructor":{"constructorId":"brp","url":"http://en.wikipedia.org/wiki/British_Racing_Partnership","name":"BRP","nationality":"British"},"grid":"11","laps":"102","status":"+3 Laps"},{"number":"11","position":"6","positionText":"6","points":"1","Driver":{"driverId":"bonnier","url":"http://en.wikipedia.org/wiki/Joakim_Bonnier","givenName":"Jo","familyName":"Bonnier","dateOfBirth":"1930-01-31","nationality":"Swedish"},"Constructor":{"constructorId":"brabham-climax","url":"http://en.wikipedia.org/wiki/Brabham","name":"Brabham-Climax","nationality":"British"},"grid":"10","laps":"101","status":"+4 Laps"},{"number":"18","position":"7","positionText":"7","points":"0","Driver":{"driverId":"baghetti","url":"http://en.wikipedia.org/wiki/Giancarlo_Baghetti","givenName":"Giancarlo","familyName":"Baghetti","dateOfBirth":"1934-12-25","nationality":"Italian"},"Constructor":{"constructorId":"brm","url":"http://en.wikipedia.org/wiki/BRM","name":"BRM","nationality":"British"},"grid":"15","laps":"96","status":"+9 Laps"},{"number":"17","position":"8","positionText":"8","points":"0","Driver":{"driverId":"hailwood","url":"http://en.wikipedia.org/wiki/Mike_Hailwood","givenName":"Mike","familyName":"Hailwood","dateOfBirth":"1940-04-02","nationality":"British"},"Constructor":{"constructorId":"lotus-brm","url":"http://en.wikipedia.org/wiki/Team_Lotus","name":"Lotus-BRM","nationality":"British"},"grid":"18","laps":"95","status":"+10 Laps"},{"number":"6","position":"9","positionText":"9","points":"0","Driver":{"driverId":"jack_brabham","url":"http://en.wikipedia.org/wiki/Jack_Brabham","givenName":"Jack","familyName":"Brabham","dateOfBirth":"1926-04-02","nationality":"Australian"},"Constructor":{"constructorId":"brabham-climax","url":"http://en.wikipedia.org/wiki/Brabham","name":"Brabham-Climax","nationality":"British"},"grid":"6","laps":"76","status":"+29 Laps"},{"number":"12","position":"10","positionText":"R","points":"0","Driver":{"driverId":"rindt","url":"http://en.wikipedia.org/wiki/Jochen_Rindt","givenName":"Jochen","familyName":"Rindt","dateOfBirth":"1942-04-18","nationality":"Austrian"},"Constructor":{"constructorId":"brabham-brm","url":"http://en.wikipedia.org/wiki/Brabham","name":"Brabham-BRM","nationality":"British"},"grid":"13","laps":"58","status":"Steering"},{"number":"10","position":"11","positionText":"R","points":"0","Driver":{"driverId":"phil_hill","url":"http://en.wikipedia.org/wiki/Phil_Hill","givenName":"Phil","familyName":"Hill","dateOfBirth":"1927-04-20","nationality":"American"},"Constructor":{"constructorId":"cooper-climax","url":"http://en.wikipedia.org/wiki/Cooper_Car_Company","name":"Cooper-Climax","nationality":"British"},"grid":"20","laps":"58","status":"Accident"},{"number":"5","position":"12","positionText":"R","points":"0","Driver":{"driverId":"gurney","url":"http://en.wikipedia.org/wiki/Dan_Gurney","givenName":"Dan","familyName":"Gurney","dateOfBirth":"1931-04-13","nationality":"American"},"Constructor":{"constructorId":"brabham-climax","url":"http://en.wikipedia.org/wiki/Brabham","name":"Brabham-Climax","nationality":"British"},"grid":"4","laps":"47","status":"Suspension"},{"number":"9","position":"13","positionText":"R","points":"0","Driver":{"driverId":"mclaren","url":"http://en.wikipedia.org/wiki/Bruce_McLaren","givenName":"Bruce","familyName":"McLaren","dateOfBirth":"1937-08-30","nationality":"New Zealander"},"Constructor":{"constructorId":"cooper-climax","url":"http://en.wikipedia.org/wiki/Cooper_Car_Company","name":"Cooper-Climax","nationality":"British"},"grid":"9","laps":"43","status":"Engine"},{"number":"2","position":"14","positionText":"R","points":"0","Driver":{"driverId":"spence","url":"http://en.wikipedia.org/wiki/Mike_Spence","givenName":"Mike","familyName":"Spence","dateOfBirth":"1936-12-30","nationality":"British"},"Constructor":{"constructorId":"lotus-climax","url":"http://en.wikipedia.org/wiki/Team_Lotus","name":"Lotus-Climax","nationality":"British"},"grid":"8","laps":"41","status":"Halfshaft"},{"number":"1","position":"15","positionText":"R","points":"0","Driver":{"driverId":"clark","url":"http://en.wikipedia.org/wiki/Jim_Clark","givenName":"Jim","familyName":"Clark","dateOfBirth":"1936-03-04","nationality":"British"},"Constructor":{"constructorId":"lotus-climax","url":"http://en.wikipedia.org/wiki/Team_Lotus","name":"Lotus-Climax","nationality":"British"},"grid":"3","laps":"40","status":"Halfshaft"},{"number":"15","position":"16","positionText":"R","points":"0","Driver":{"driverId":"trevor_taylor","url":"http://en.wikipedia.org/wiki/Trevor_Taylor","givenName":"Trevor","familyName":"Taylor","dateOfBirth":"1936-12-26","nationality":"British"},"Constructor":{"constructorId":"brp","url":"http://en.wikipedia.org/wiki/British_Racing_Partnership","name":"BRP","nationality":"British"},"grid":"16","laps":"21","status":"Suspension"},{"number":"20","position":"17","positionText":"R","points":"0","Driver":{"driverId":"siffert","url":"http://en.wikipedia.org/wiki/Jo_Siffert","givenName":"Jo","familyName":"Siffert","dateOfBirth":"1936-07-07","nationality":"Swiss"},"Constructor":{"constructorId":"brabham-brm","url":"http://en.wikipedia.org/wiki/Brabham","name":"Brabham-BRM","nationality":"British"},"grid":"12","laps":"18","status":"Accident"},{"number":"7","position":"18","positionText":"R","points":"0","Driver":{"driverId":"surtees","url":"http://en.wikipedia.org/wiki/John_Surtees","givenName":"John","familyName":"Surtees","dateOfBirth":"1934-02-11","nationality":"British"},"Constructor":{"constructorId":"ferrari","url":"http://en.wikipedia.org/wiki/Scuderia_Ferrari","name":"Ferrari","nationality":"Italian"},"grid":"2","laps":"9","status":"Suspension"},{"number":"16","position":"19","positionText":"R","points":"0","Driver":{"driverId":"amon","url":"http://en.wikipedia.org/wiki/Chris_Amon","givenName":"Chris","familyName":"Amon","dateOfBirth":"1943-07-20","nationality":"New Zealander"},"Constructor":{"constructorId":"lotus-climax","url":"http://en.wikipedia.org/wiki/Team_Lotus","name":"Lotus-Climax","nationality":"British"},"grid":"17","laps":"7","status":"Engine"},{"number":"3","position":"20","positionText":"R","points":"0","Driver":{"driverId":"hill","url":"http://en.wikipedia.org/wiki/Graham_Hill","givenName":"Graham","familyName":"Hill","dateOfBirth":"1929-02-15","nationality":"British"},"Constructor":{"constructorId":"brm","url":"http://en.wikipedia.org/wiki/BRM","name":"BRM","nationality":"British"},"grid":"1","laps":"5","status":"Distributor"}]}]}}}