{"MRData":{"xmlns":"","series":"f1","url":"https://api.jolpi.ca/ergast/f1/1950/drivers/biondetti/results/","limit":"30","offset":"0","total":"1","RaceTable":{"season":"1950","driverId":"biondetti","Races":[{"season":"1950","round":"7","url":"https://en.wikipedia.org/wiki/1950_Italian_Grand_Prix","raceName":"Italian Grand Prix","Circuit":{"circuitId":"monza","url":"https://en.wikipedia.org/wiki/Monza_Circuit","circuitName":"Autodromo Nazionale di Monza","Location":{"lat":"45.6156","long":"9.28111","locality":"Monza","country":"Italy"}},"date":"1950-09-03","Results":[{"number":"22","position":"18","positionText":"R","points":"0","Driver":{"driverId":"biondetti","url":"http://en.wikipedia.org/wiki/Clemente_Biondetti","givenName":"Clemente","familyName":"Biondetti","dateOfBirth":"1898-08-18","nationality":"Italian"},"Constructor":{"constructorId":"ferrari","url":"http://en.wikipedia.org/wiki/Scuderia_Ferrari","name":"Ferrari","nationality":"Italian"},"grid":"25","laps":"17","status":"Engine"}]}]}}}