{"MRData":{"xmlns":"","series":"f1","url":"https://api.jolpi.ca/ergast/f1/1983/constructors.json","limit":"30","offset":"0","total":"16","ConstructorTable":{"season":"1983","Constructors":[{"constructorId":"alfa","url":"http://en.wikipedia.org/wiki/Alfa_Romeo_in_Formula_One","name":"Alfa Romeo","nationality":"Swiss"},{"constructorId":"arrows","url":"http://en.wikipedia.org/wiki/Arrows_Grand_Prix_International","name":"Arrows","nationality":"British"},{"constructorId":"ats","url":"http://en.wikipedia.org/wiki/ATS_(wheels)","name":"ATS","nationality":"Italian"},{"constructorId":"brabham","url":"http://en.wikipedia.org/wiki/Brabham","name":"Brabham","nationality":"British"},{"constructorId":"ferrari","url":"http://en.wikipedia.org/wiki/Scuderia_Ferrari","name":"Ferrari","nationality":"Italian"},{"constructorId":"ligier","url":"http://en.wikipedia.org/wiki/Ligier","name":"Ligier","nationality":"French"},{"constructorId":"mclaren","url":"http://en.wikipedia.org/wiki/McLaren","name":"McLaren","nationality":"British"},{"constructorId":"osella","url":"http://en.wikipedia.org/wiki/Osella","name":"Osella","nationality":"Italian"},{"constructorId":"ram","url":"http://en.wikipedia.org/wiki/RAM_Racing","name":"RAM","nationality":"British"},{"constructorId":"renault","url":"http://en.wikipedia.org/wiki/Renault_in_Formula_One","name":"Renault","nationality":"French"},{"constructorId":"spirit","url":"http://en.wikipedia.org/wiki/Spirit_(racing_team)","name":"Spirit","nationality":"British"},{"constructorId":"team_lotus","url":"http://en.wikipedia.org/wiki/Team_Lotus","name":"Team Lotus","nationality":"British"},{"constructorId":"theodore","url":"http://en.wikipedia.org/wiki/Theodore_Racing","name":"Theodore","nationality":"Hong Kong"},{"constructorId":"toleman","url":"http://en.wikipedia.org/wiki/Toleman","name":"Toleman","nationality":"British"},{"constructorId":"tyrrell","url":"http://en.wikipedia.org/wiki/Tyrrell_Racing","name":"Tyrrell","nationality":"British"},{"constructorId":"williams","url":"http://en.wikipedia.org/wiki/Williams_Grand_Prix_Engineering","name":"Williams","nationality":"British"}]}}}